MANIFEST.in
setup.py
crow/__init__.py
crow.egg-info/PKG-INFO
crow.egg-info/SOURCES.txt
crow.egg-info/dependency_links.txt
crow.egg-info/entry_points.txt
crow.egg-info/requires.txt
crow.egg-info/top_level.txt
crow/agent/__init__.py
crow/agent/base.py
crow/agent/config.py
crow/agent/runner.py