Metadata-Version: 1.1
Name: crow
Version: 0.1.0
Summary: Service ochestration based on etcd
Home-page: https://github.com/hurrycane/crow
Author: Bogdan Gaza
Author-email: bc.gaza@gmail.com
License: UNKNOWN
Platform: any
Classifier: Topic :: System :: Distributed Computing
Classifier: Topic :: Software Development :: Libraries
Classifier: License :: OSI Approved :: MIT License
Classifier: Topic :: Database :: Front-Ends
